libvanitas-0.1.1.dist-info/METADATA
libvanitas-0.1.1.dist-info/WHEEL
libvanitas/__init__.py
libvanitas/libvanitas.cp310-win_amd64.pyd
libvanitas-0.1.1.dist-info/RECORD
