Metadata-Version: 2.3
Name: libvanitas
Version: 0.1.1
Summary: Python wrapper for the whitespace library
Author-email: Ect07 <ect@vivaldi.net>
License: MIT
Project-URL: Homepage, https://github.com/rHanbowChic/libvanitas
Project-URL: Repository, https://github.com/rHanbowChic/libvanitas.git
Project-URL: Issues, https://github.com/rHanbowChic/libvanitas/issues
